README.md
setup.py
gpam_pre_processing_ner.egg-info/PKG-INFO
gpam_pre_processing_ner.egg-info/SOURCES.txt
gpam_pre_processing_ner.egg-info/dependency_links.txt
gpam_pre_processing_ner.egg-info/requires.txt
gpam_pre_processing_ner.egg-info/top_level.txt
pre_processing_ner/__init__.py
pre_processing_ner/ner.py
pre_processing_ner/special_tokens.py
pre_processing_ner/utils.py
pre_processing_ner/lenerbr/__init__.py
pre_processing_ner/lenerbr/base_model.py
pre_processing_ner/lenerbr/config.py
pre_processing_ner/lenerbr/data_utils.py
pre_processing_ner/lenerbr/general_utils.py
pre_processing_ner/lenerbr/ner_model.py