Metadata-Version: 1.0
Name: gpam-pre-processing-ner
Version: 0.0.2
Summary: GPAM ner pre-processing
Home-page: https://gitlab.com/gpam/services/pre-processing-ner
Author: GPAM
Author-email: gpam@gmail.com
License: UNKNOWN
Platform: UNKNOWN
